<?xml version="1.0" encoding="utf-8" ?>
<c2eventsheet>
    <!--All the 'name' attributes are ignored by Construct 2 - they are there for readability only.-->
    <name>Login</name>
    <events>
        <variable constant="0" name="LogInPressed" sid="633151059201870" static="0" type="number">0</variable>
        <include>Globals</include>
        <include>GLOBAL EVENTS</include>
        <event-block sid="381039369065431">
            <conditions>
                <condition id="-2" name="On start of layout" sid="194558057525926" type="System" />
            </conditions>
            <actions>
                <action id="1" name="Set cursor from sprite" sid="635302780066429" type="Mouse">
                    <param id="0" name="Sprite">Cursor</param>
                </action>
                <action id="-27" name="Set effect enabled" sid="663793346729914" type="Button">
                    <param id="0" name="Mode">0</param>
                    <param id="1" name="Effect">&quot;DISABLED&quot;</param>
                </action>
                <action id="-27" name="Set effect enabled" sid="453977206613426" type="Button">
                    <param id="0" name="Mode">0</param>
                    <param id="1" name="Effect">&quot;SELECTED&quot;</param>
                </action>
                <action id="0" name="Set text" sid="245863007360721" type="MPUsernameBox">
                    <param id="0" name="Text">MP_USERNAME</param>
                </action>
                <action id="0" name="Set text" sid="894070138618959" type="PasswordTextbox">
                    <param id="0" name="Text">Password</param>
                </action>
                <action id="0" name="Set text" sid="342084768014818" type="VersionText">
                    <param id="0" name="Text">&quot;Ver. &quot;&amp;projectversion</param>
                </action>
                <action id="0" name="Play" sid="696991350679311" type="Audio">
                    <param id="0" name="Audio file">through space</param>
                    <param id="2" name="Loop">1</param>
                    <param id="3" name="Volume">MusicVolume</param>
                    <param id="1" name="Tag (optional)">&quot;Music&quot;</param>
                </action>
                <action id="-9" name="Set value" sid="306996954523774" type="System">
                    <param id="0" name="Variable">MaxSelectable</param>
                    <param id="1" name="Value">13</param>
                </action>
                <action id="-9" name="Set value" sid="899788200165506" type="System">
                    <param id="0" name="Variable">MinSelectable</param>
                    <param id="1" name="Value">13</param>
                </action>
                <action id="-9" name="Set value" sid="708790169138344" type="System">
                    <param id="0" name="Variable">Selected</param>
                    <param id="1" name="Value">13</param>
                </action>
            </actions>
        </event-block>
        <event-block any="1" sid="960404780860785">
            <conditions>
                <condition id="6" name="On object clicked" sid="903523887183924" type="Mouse">
                    <param id="0" name="Mouse button">0</param>
                    <param id="1" name="Click type">0</param>
                    <param id="2" name="Object clicked">LoginButtonText</param>
                </condition>
                <condition id="17" name="On tap object" sid="172947396736233" type="Touch">
                    <param id="0" name="Object">LoginButtonText</param>
                </condition>
                <condition id="0" name="On key pressed" sid="399000624152562" type="Keyboard">
                    <param id="0" name="Key">13 (Return)</param>
                </condition>
                <condition id="6" name="On button pressed" sid="806574981794907" type="Gamepad">
                    <param id="0" name="Gamepad">0</param>
                    <param id="1" name="Button">0</param>
                </condition>
            </conditions>
            <actions>
                <action disabled="1" id="0" name="Set text" sid="693044966930996" type="LoginStatusText">
                    <param id="0" name="Text">&quot;&quot;</param>
                </action>
                <action disabled="1" id="-15" name="Set visible" sid="316171262886779" type="LoginStatusText">
                    <param id="0" name="Visibility">0</param>
                </action>
            </actions>
            <sub-events>
                <event-block sid="484185296406507">
                    <conditions>
                        <condition id="-14" inverted="1" name="Compare variable" sid="242284656868133" type="System">
                            <param id="0" name="Variable">MP_USERNAME</param>
                            <param id="1" name="Comparison">0</param>
                            <param id="2" name="Value">&quot;&quot;</param>
                        </condition>
                        <condition id="-14" inverted="1" name="Compare variable" sid="892782857935498" type="System">
                            <param id="0" name="Variable">Password</param>
                            <param id="1" name="Comparison">0</param>
                            <param id="2" name="Value">&quot;&quot;</param>
                        </condition>
                    </conditions>
                    <actions>
                        <action id="0" name="Request URL" sid="530211676924538" type="AJAX">
                            <param id="0" name="Tag">&quot;Login&quot;</param>
                            <param id="1" name="URL">&quot;http://jordan.bnettech.pw/login.php?fname=&quot;&amp;MP_USERNAME&amp;&quot;&amp;fpass=&quot;&amp;Password</param>
                        </action>
                        <action id="14" name="Log" sid="722469176692243" type="Browser">
                            <param id="0" name="Type">0</param>
                            <param id="1" name="Message">&quot;Requesting Login data&quot;</param>
                        </action>
                        <action id="-9" name="Set value" sid="381294420996179" type="System">
                            <param id="0" name="Variable">LogInPressed</param>
                            <param id="1" name="Value">1</param>
                        </action>
                        <action id="4" name="Set enabled" sid="695683462188560" type="PasswordTextbox">
                            <param id="0" name="Mode">0</param>
                        </action>
                    </actions>
                </event-block>
            </sub-events>
        </event-block>
        <event-block any="1" sid="757022721972450">
            <conditions>
                <condition id="-14" name="Compare variable" sid="776617465899596" type="System">
                    <param id="0" name="Variable">MP_USERNAME</param>
                    <param id="1" name="Comparison">0</param>
                    <param id="2" name="Value">&quot;&quot;</param>
                </condition>
                <condition id="-14" name="Compare variable" sid="648123406372459" type="System">
                    <param id="0" name="Variable">Password</param>
                    <param id="1" name="Comparison">0</param>
                    <param id="2" name="Value">&quot;&quot;</param>
                </condition>
                <condition id="-14" name="Compare variable" sid="592588749446897" type="System">
                    <param id="0" name="Variable">LogInPressed</param>
                    <param id="1" name="Comparison">0</param>
                    <param id="2" name="Value">1</param>
                </condition>
            </conditions>
            <actions />
            <sub-events>
                <event-block sid="807607406841737">
                    <conditions>
                        <condition id="-14" name="Pick by unique ID" sid="595881988974093" type="Button">
                            <param id="0" name="Unique ID">178</param>
                        </condition>
                    </conditions>
                    <actions>
                        <action id="-27" name="Set effect enabled" sid="883842528365303" type="Button">
                            <param id="0" name="Mode">1</param>
                            <param id="1" name="Effect">&quot;DISABLED&quot;</param>
                        </action>
                    </actions>
                </event-block>
            </sub-events>
        </event-block>
        <event-block sid="835552944968632">
            <conditions>
                <condition id="-22" name="Else" sid="131660546768064" type="System" />
            </conditions>
            <actions />
            <sub-events>
                <event-block sid="766815484691958">
                    <conditions>
                        <condition id="-14" name="Pick by unique ID" sid="204136578328258" type="Button">
                            <param id="0" name="Unique ID">178</param>
                        </condition>
                    </conditions>
                    <actions>
                        <action id="-27" name="Set effect enabled" sid="792608861961232" type="Button">
                            <param id="0" name="Mode">0</param>
                            <param id="1" name="Effect">&quot;DISABLED&quot;</param>
                        </action>
                    </actions>
                </event-block>
            </sub-events>
        </event-block>
        <event-block sid="238366688417062">
            <conditions>
                <condition id="1" name="On text changed" sid="376790474792806" type="PasswordTextbox" />
            </conditions>
            <actions>
                <action id="-9" name="Set value" sid="474427096625542" type="System">
                    <param id="0" name="Variable">Password</param>
                    <param id="1" name="Value">PasswordTextbox.Text</param>
                </action>
                <action disabled="1" id="14" name="Log" sid="850457658240517" type="Browser">
                    <param id="0" name="Type">0</param>
                    <param id="1" name="Message">&quot;Setting Password: &quot;&amp;Password</param>
                </action>
            </actions>
        </event-block>
        <event-block sid="980790579221431">
            <conditions>
                <condition id="1" name="On text changed" sid="490215323677538" type="MPUsernameBox" />
            </conditions>
            <actions>
                <action id="-9" name="Set value" sid="130886332601801" type="System">
                    <param id="0" name="Variable">MP_USERNAME</param>
                    <param id="1" name="Value">MPUsernameBox.Text</param>
                </action>
                <action disabled="1" id="14" name="Log" sid="116797368467061" type="Browser">
                    <param id="0" name="Type">0</param>
                    <param id="1" name="Message">&quot;Setting MP_USERNAME: &quot;&amp;MP_USERNAME</param>
                </action>
            </actions>
        </event-block>
        <event-block sid="510626629234227">
            <conditions>
                <condition id="1" name="On error" sid="607089936761184" type="AJAX">
                    <param id="0" name="Tag">&quot;Login&quot;</param>
                </condition>
            </conditions>
            <actions>
                <action id="0" name="Set text" sid="487767627443342" type="LoginStatusText">
                    <param id="0" name="Text">&quot;Error: Cannot connect to server!&quot;</param>
                </action>
                <action id="-15" name="Set visible" sid="393168488274731" type="LoginStatusText">
                    <param id="0" name="Visibility">1</param>
                </action>
                <action id="4" name="Set enabled" sid="506755803448051" type="PasswordTextbox">
                    <param id="0" name="Mode">1</param>
                </action>
            </actions>
        </event-block>
        <event-block sid="469731792521585">
            <conditions>
                <condition id="1" name="On error" sid="205650631266618" type="AJAX">
                    <param id="0" name="Tag">&quot;Level&quot;</param>
                </condition>
            </conditions>
            <actions>
                <action id="0" name="Set text" sid="153331077225762" type="LoginStatusText">
                    <param id="0" name="Text">&quot;Error: Level not defined!&quot;</param>
                </action>
                <action id="-15" name="Set visible" sid="524245281986408" type="LoginStatusText">
                    <param id="0" name="Visibility">1</param>
                </action>
                <action id="4" name="Set enabled" sid="963035822419406" type="PasswordTextbox">
                    <param id="0" name="Mode">1</param>
                </action>
            </actions>
        </event-block>
        <event-block sid="815467107715219">
            <conditions>
                <condition id="1" name="On error" sid="467975152964609" type="AJAX">
                    <param id="0" name="Tag">&quot;Kills&quot;</param>
                </condition>
            </conditions>
            <actions>
                <action id="0" name="Set text" sid="921740844290909" type="LoginStatusText">
                    <param id="0" name="Text">&quot;Error: Kills not defined!&quot;</param>
                </action>
                <action id="-15" name="Set visible" sid="476675027326701" type="LoginStatusText">
                    <param id="0" name="Visibility">1</param>
                </action>
                <action id="4" name="Set enabled" sid="619672677855160" type="PasswordTextbox">
                    <param id="0" name="Mode">1</param>
                </action>
            </actions>
        </event-block>
        <event-block sid="584202439264588">
            <conditions>
                <condition id="1" name="On error" sid="505292268490538" type="AJAX">
                    <param id="0" name="Tag">&quot;Deaths&quot;</param>
                </condition>
            </conditions>
            <actions>
                <action id="0" name="Set text" sid="445888381204019" type="LoginStatusText">
                    <param id="0" name="Text">&quot;Error: Deaths not defined!&quot;</param>
                </action>
                <action id="-15" name="Set visible" sid="275817146275659" type="LoginStatusText">
                    <param id="0" name="Visibility">1</param>
                </action>
                <action id="4" name="Set enabled" sid="697645658776390" type="PasswordTextbox">
                    <param id="0" name="Mode">1</param>
                </action>
            </actions>
        </event-block>
        <event-block sid="494320970644741">
            <conditions>
                <condition id="1" name="On error" sid="197225038817903" type="AJAX">
                    <param id="0" name="Tag">&quot;Prefix&quot;</param>
                </condition>
            </conditions>
            <actions>
                <action id="0" name="Set text" sid="789176996955991" type="LoginStatusText">
                    <param id="0" name="Text">&quot;Error: Prefix not defined!&quot;</param>
                </action>
                <action id="-15" name="Set visible" sid="229878907519639" type="LoginStatusText">
                    <param id="0" name="Visibility">1</param>
                </action>
                <action id="4" name="Set enabled" sid="374410533198315" type="PasswordTextbox">
                    <param id="0" name="Mode">1</param>
                </action>
            </actions>
        </event-block>
        <event-block sid="721087981357356">
            <conditions>
                <condition id="0" name="On completed" sid="590835918831354" type="AJAX">
                    <param id="0" name="Tag">&quot;Login&quot;</param>
                </condition>
            </conditions>
            <actions>
                <action id="0" name="Request URL" sid="715893377206807" type="AJAX">
                    <param id="0" name="Tag">&quot;Level&quot;</param>
                    <param id="1" name="URL">&quot;http://jordan.bnettech.pw/getLevel.php?fname=&quot;&amp;MP_USERNAME&amp;&quot;&amp;fpass=&quot;&amp;Password</param>
                </action>
                <action id="-9" name="Set value" sid="800996759641584" type="System">
                    <param id="0" name="Variable">UserID</param>
                    <param id="1" name="Value">AJAX.LastData</param>
                </action>
                <action id="14" name="Log" sid="879559826255426" type="Browser">
                    <param id="0" name="Type">0</param>
                    <param id="1" name="Message">&quot;AJAX recieved value: &quot;&amp;AJAX.LastData</param>
                </action>
            </actions>
        </event-block>
        <event-block sid="623189177880385">
            <conditions>
                <condition id="0" name="On completed" sid="972167480797963" type="AJAX">
                    <param id="0" name="Tag">&quot;Level&quot;</param>
                </condition>
            </conditions>
            <actions>
                <action id="0" name="Request URL" sid="797003452130188" type="AJAX">
                    <param id="0" name="Tag">&quot;Kills&quot;</param>
                    <param id="1" name="URL">&quot;http://jordan.bnettech.pw/getKills.php?fname=&quot;&amp;MP_USERNAME&amp;&quot;&amp;fpass=&quot;&amp;Password</param>
                </action>
                <action id="-9" name="Set value" sid="869336936198881" type="System">
                    <param id="0" name="Variable">MPLevel</param>
                    <param id="1" name="Value">AJAX.LastData</param>
                </action>
                <action id="14" name="Log" sid="825993632947067" type="Browser">
                    <param id="0" name="Type">0</param>
                    <param id="1" name="Message">&quot;AJAX recieved value: &quot;&amp;AJAX.LastData</param>
                </action>
            </actions>
        </event-block>
        <event-block sid="686196361480644">
            <conditions>
                <condition id="0" name="On completed" sid="111751422956180" type="AJAX">
                    <param id="0" name="Tag">&quot;Kills&quot;</param>
                </condition>
            </conditions>
            <actions>
                <action id="0" name="Request URL" sid="516605790778209" type="AJAX">
                    <param id="0" name="Tag">&quot;Deaths&quot;</param>
                    <param id="1" name="URL">&quot;http://jordan.bnettech.pw/getDeaths.php?fname=&quot;&amp;MP_USERNAME&amp;&quot;&amp;fpass=&quot;&amp;Password</param>
                </action>
                <action id="-9" name="Set value" sid="346387519635233" type="System">
                    <param id="0" name="Variable">TotalKills</param>
                    <param id="1" name="Value">AJAX.LastData</param>
                </action>
                <action id="0" name="Set item" sid="109552025378144" type="LocalStorage">
                    <param id="0" name="Key">&quot;MP Kills&quot;</param>
                    <param id="1" name="Value">TotalKills</param>
                </action>
                <action id="14" name="Log" sid="654075919826094" type="Browser">
                    <param id="0" name="Type">0</param>
                    <param id="1" name="Message">&quot;AJAX recieved value: &quot;&amp;AJAX.LastData</param>
                </action>
            </actions>
        </event-block>
        <event-block sid="145904525642333">
            <conditions>
                <condition id="0" name="On completed" sid="568251657819419" type="AJAX">
                    <param id="0" name="Tag">&quot;Deaths&quot;</param>
                </condition>
            </conditions>
            <actions>
                <action id="0" name="Request URL" sid="378443076303473" type="AJAX">
                    <param id="0" name="Tag">&quot;Prefix&quot;</param>
                    <param id="1" name="URL">&quot;http://jordan.bnettech.pw/getPrefix.php?fname=&quot;&amp;MP_USERNAME&amp;&quot;&amp;fpass=&quot;&amp;Password</param>
                </action>
                <action id="-9" name="Set value" sid="874756243338375" type="System">
                    <param id="0" name="Variable">TotalDeaths</param>
                    <param id="1" name="Value">AJAX.LastData</param>
                </action>
                <action id="0" name="Set item" sid="711540258387526" type="LocalStorage">
                    <param id="0" name="Key">&quot;MP Deaths&quot;</param>
                    <param id="1" name="Value">TotalDeaths</param>
                </action>
                <action id="14" name="Log" sid="597932470380046" type="Browser">
                    <param id="0" name="Type">0</param>
                    <param id="1" name="Message">&quot;AJAX recieved value: &quot;&amp;AJAX.LastData</param>
                </action>
            </actions>
        </event-block>
        <event-block sid="146775284533437">
            <conditions>
                <condition id="0" name="On completed" sid="421257956087533" type="AJAX">
                    <param id="0" name="Tag">&quot;Prefix&quot;</param>
                </condition>
            </conditions>
            <actions>
                <action id="-9" name="Set value" sid="904114598145034" type="System">
                    <param id="0" name="Variable">Prefix</param>
                    <param id="1" name="Value">AJAX.LastData</param>
                </action>
                <action id="14" name="Log" sid="296394461426971" type="Browser">
                    <param id="0" name="Type">0</param>
                    <param id="1" name="Message">&quot;AJAX recieved value: &quot;&amp;AJAX.LastData</param>
                </action>
                <action id="0" name="Call function" sid="305116289709061" type="f">
                    <param id="0" name="Name">&quot;Login&quot;</param>
                    <param id="1" name="Parameter {n}"></param>
                </action>
            </actions>
        </event-block>
        <event-block sid="997412396445918">
            <conditions>
                <condition id="0" name="On function" sid="631586539620686" type="f">
                    <param id="0" name="Name">&quot;Login&quot;</param>
                </condition>
            </conditions>
            <actions />
            <sub-events>
                <event-block sid="384628668214762">
                    <conditions>
                        <condition id="-14" name="Compare variable" sid="864015102112716" type="System">
                            <param id="0" name="Variable">UserID</param>
                            <param id="1" name="Comparison">4</param>
                            <param id="2" name="Value">0</param>
                        </condition>
                        <condition id="-14" name="Compare variable" sid="930053202062450" type="System">
                            <param id="0" name="Variable">MPLevel</param>
                            <param id="1" name="Comparison">4</param>
                            <param id="2" name="Value">0</param>
                        </condition>
                    </conditions>
                    <actions>
                        <action id="0" name="Set item" sid="873868484420667" type="LocalStorage">
                            <param id="0" name="Key">&quot;MP USERNAME&quot;</param>
                            <param id="1" name="Value">MP_USERNAME</param>
                        </action>
                        <action id="-9" name="Set value" sid="941882784235381" type="System">
                            <param id="0" name="Variable">NextLayout</param>
                            <param id="1" name="Value">&quot;Main Menu&quot;</param>
                        </action>
                        <action id="-2" name="Go to layout" sid="135826457489406" type="System">
                            <param id="0" name="Layout">Loading</param>
                        </action>
                        <action id="14" name="Log" sid="680122724761544" type="Browser">
                            <param id="0" name="Type">0</param>
                            <param id="1" name="Message">&quot;Going to &quot;&amp;NextLayout</param>
                        </action>
                        <action id="-9" name="Set value" sid="656671827555999" type="System">
                            <param id="0" name="Variable">Offline</param>
                            <param id="1" name="Value">0</param>
                        </action>
                        <action id="-9" name="Set value" sid="103143684470399" type="System">
                            <param id="0" name="Variable">LogInPressed</param>
                            <param id="1" name="Value">0</param>
                        </action>
                    </actions>
                </event-block>
                <event-block sid="856462405915665">
                    <conditions>
                        <condition id="-22" name="Else" sid="767855460834457" type="System" />
                        <condition id="-14" inverted="1" name="Compare variable" sid="458269605538277" type="System">
                            <param id="0" name="Variable">UserID</param>
                            <param id="1" name="Comparison">4</param>
                            <param id="2" name="Value">0</param>
                        </condition>
                    </conditions>
                    <actions>
                        <action id="0" name="Set text" sid="617705017940600" type="LoginStatusText">
                            <param id="0" name="Text">&quot;Error: Username or Password is incorrect!&quot;</param>
                        </action>
                        <action id="-15" name="Set visible" sid="947132837570877" type="LoginStatusText">
                            <param id="0" name="Visibility">1</param>
                        </action>
                        <action id="-9" name="Set value" sid="420915464961940" type="System">
                            <param id="0" name="Variable">LogInPressed</param>
                            <param id="1" name="Value">0</param>
                        </action>
                        <action id="4" name="Set enabled" sid="381203157111500" type="PasswordTextbox">
                            <param id="0" name="Mode">1</param>
                        </action>
                    </actions>
                </event-block>
                <event-block sid="987233745312966">
                    <conditions>
                        <condition id="-22" name="Else" sid="609386018015274" type="System" />
                        <condition id="-14" inverted="1" name="Compare variable" sid="166975990564230" type="System">
                            <param id="0" name="Variable">MPLevel</param>
                            <param id="1" name="Comparison">4</param>
                            <param id="2" name="Value">0</param>
                        </condition>
                    </conditions>
                    <actions>
                        <action id="0" name="Set text" sid="502369637669360" type="LoginStatusText">
                            <param id="0" name="Text">&quot;Error: Level cannot be 0!&quot;</param>
                        </action>
                        <action id="-15" name="Set visible" sid="133114136971551" type="LoginStatusText">
                            <param id="0" name="Visibility">1</param>
                        </action>
                        <action id="-9" name="Set value" sid="282067859300321" type="System">
                            <param id="0" name="Variable">LogInPressed</param>
                            <param id="1" name="Value">0</param>
                        </action>
                        <action id="4" name="Set enabled" sid="280707964807684" type="PasswordTextbox">
                            <param id="0" name="Mode">1</param>
                        </action>
                    </actions>
                </event-block>
            </sub-events>
        </event-block>
        <event-block any="1" sid="892276598979062">
            <conditions>
                <condition id="6" name="On object clicked" sid="323263781562903" type="Mouse">
                    <param id="0" name="Mouse button">0</param>
                    <param id="1" name="Click type">0</param>
                    <param id="2" name="Object clicked">SignUpText</param>
                </condition>
                <condition id="17" name="On tap object" sid="140424714861092" type="Touch">
                    <param id="0" name="Object">SignUpText</param>
                </condition>
            </conditions>
            <actions>
                <action id="8" name="Open URL in new window" sid="835461752818040" type="Browser">
                    <param id="0" name="URL">&quot;http://jordan.bnettech.pw/Signup.html&quot;</param>
                    <param id="1" name="Tag">&quot;NewWindow&quot;</param>
                </action>
            </actions>
        </event-block>
        <event-block any="1" sid="268146003876297">
            <conditions>
                <condition id="6" name="On object clicked" sid="385542548029453" type="Mouse">
                    <param id="0" name="Mouse button">0</param>
                    <param id="1" name="Click type">0</param>
                    <param id="2" name="Object clicked">OfflineButtonText</param>
                </condition>
                <condition id="17" name="On tap object" sid="922621114522891" type="Touch">
                    <param id="0" name="Object">OfflineButtonText</param>
                </condition>
            </conditions>
            <actions>
                <action id="-9" name="Set value" sid="976829042102999" type="System">
                    <param id="0" name="Variable">Offline</param>
                    <param id="1" name="Value">1</param>
                </action>
                <action id="-16" name="Wait" sid="930993307440626" type="System">
                    <param id="0" name="Seconds">0</param>
                </action>
                <action id="-9" name="Set value" sid="831452542974459" type="System">
                    <param id="0" name="Variable">Level</param>
                    <param id="1" name="Value">0</param>
                </action>
                <action id="-9" name="Set value" sid="597595791925428" type="System">
                    <param id="0" name="Variable">TotalKills</param>
                    <param id="1" name="Value">0</param>
                </action>
                <action id="-9" name="Set value" sid="154115374189346" type="System">
                    <param id="0" name="Variable">TotalDeaths</param>
                    <param id="1" name="Value">0</param>
                </action>
                <action id="-16" name="Wait" sid="317320388098599" type="System">
                    <param id="0" name="Seconds">0</param>
                </action>
                <action id="-9" name="Set value" sid="532067562454272" type="System">
                    <param id="0" name="Variable">NextLayout</param>
                    <param id="1" name="Value">&quot;Main Menu&quot;</param>
                </action>
                <action id="14" name="Log" sid="368617274790602" type="Browser">
                    <param id="0" name="Type">0</param>
                    <param id="1" name="Message">&quot;Going to &quot;&amp;NextLayout</param>
                </action>
                <action id="-2" name="Go to layout" sid="485449262969362" type="System">
                    <param id="0" name="Layout">Loading</param>
                </action>
            </actions>
        </event-block>
        <event-block sid="462742480338745">
            <conditions>
                <condition id="2" name="Mouse button is down" sid="723496662034267" type="Mouse">
                    <param id="0" name="Mouse button">0</param>
                </condition>
            </conditions>
            <actions>
                <action id="-16" name="Wait" sid="810810222133002" type="System">
                    <param id="0" name="Seconds">0</param>
                </action>
                <action id="1" name="Set cursor from sprite" sid="774394147119910" type="Mouse">
                    <param id="0" name="Sprite">CursorInverted</param>
                </action>
                <action id="-16" name="Wait" sid="639402983172783" type="System">
                    <param id="0" name="Seconds">0</param>
                </action>
            </actions>
        </event-block>
        <event-block sid="702232158243386">
            <conditions>
                <condition id="-22" name="Else" sid="347276612402542" type="System" />
            </conditions>
            <actions>
                <action id="-16" name="Wait" sid="972237124214735" type="System">
                    <param id="0" name="Seconds">0</param>
                </action>
                <action id="1" name="Set cursor from sprite" sid="968695815699927" type="Mouse">
                    <param id="0" name="Sprite">Cursor</param>
                </action>
                <action id="-16" name="Wait" sid="759925716313574" type="System">
                    <param id="0" name="Seconds">0</param>
                </action>
            </actions>
        </event-block>
        <event-block sid="185198564206126">
            <conditions>
                <condition id="0" name="On completed" sid="790468107550056" type="AJAX">
                    <param id="0" name="Tag">&quot;Prefix&quot;</param>
                </condition>
            </conditions>
            <actions>
                <action id="-9" name="Set value" sid="282875126776240" type="System">
                    <param id="0" name="Variable">Prefix</param>
                    <param id="1" name="Value">AJAX.LastData</param>
                </action>
                <action id="14" name="Log" sid="478413723665278" type="Browser">
                    <param id="0" name="Type">0</param>
                    <param id="1" name="Message">&quot;AJAX recieved value: &quot;&amp;AJAX.LastData</param>
                </action>
                <action id="0" name="Call function" sid="921460202553470" type="f">
                    <param id="0" name="Name">&quot;Login&quot;</param>
                    <param id="1" name="Parameter {n}"></param>
                </action>
            </actions>
        </event-block>
        <event-group description="" disabled="1" sid="321303998226409" title="Security Check">
            <sub-events>
                <variable constant="1" name="Name" sid="830113895587037" static="1" type="text">http://</variable>
                <variable constant="1" name="TXT" sid="884900743571238" static="1" type="text">jordan</variable>
                <variable constant="1" name="Red" sid="416061996477154" static="1" type="text">.bnettech.pw</variable>
                <variable constant="1" name="WARS" sid="569106666672376" static="1" type="text">/AlienWars</variable>
                <event-block sid="630781365572186">
                    <conditions>
                        <condition id="-6" name="Every X seconds" sid="451432254176166" type="System">
                            <param id="0" name="Interval (seconds)">1</param>
                        </condition>
                    </conditions>
                    <actions>
                        <action id="14" name="Log" sid="945077087741743" type="Browser">
                            <param id="0" name="Type">0</param>
                            <param id="1" name="Message">&quot;checking security of: &quot;&amp;Browser.URL</param>
                        </action>
                    </actions>
                    <sub-events>
                        <event-block any="1" sid="404171800659943">
                            <conditions>
                                <condition id="-8" inverted="1" name="Compare two values" sid="437517877021781" type="System">
                                    <param id="0" name="First value">Browser.URL</param>
                                    <param id="1" name="Comparison">0</param>
                                    <param id="2" name="Second value">NAME&amp;TXT&amp;RED&amp;WARS&amp;&quot;/&quot;</param>
                                </condition>
                            </conditions>
                            <actions />
                            <sub-events>
                                <event-block any="1" sid="250279800567271">
                                    <conditions>
                                        <condition id="-18" inverted="1" name="Is in preview" sid="752656920305643" type="System" />
                                        <condition id="-32" inverted="1" name="Is on platform" sid="930850285584935" type="System">
                                            <param id="0" name="Platform">10</param>
                                        </condition>
                                        <condition id="-32" inverted="1" name="Is on platform" sid="558352462573140" type="System">
                                            <param id="0" name="Platform">13</param>
                                        </condition>
                                    </conditions>
                                    <actions>
                                        <action id="0" name="Set text" sid="330387242707950" type="LoginTitleText">
                                            <param id="0" name="Text">&quot;SECURITY CHECK FAILED!&quot;</param>
                                        </action>
                                        <action id="-3" name="Set position" sid="573432957692424" type="LoginTitleText">
                                            <param id="0" name="X">LayoutWidth/2</param>
                                            <param id="1" name="Y">LayoutHeight/2</param>
                                        </action>
                                        <action id="-9" name="Destroy" sid="755179453456430" type="PasswordTextbox" />
                                        <action id="-9" name="Destroy" sid="807317412029439" type="MPUsernameBox" />
                                        <action id="-9" name="Destroy" sid="695067762098413" type="Button" />
                                        <action id="-9" name="Destroy" sid="815537337668649" type="LoginButtonText" />
                                        <action id="14" name="Log" sid="489221455735361" type="Browser">
                                            <param id="0" name="Type">2</param>
                                            <param id="1" name="Message">&quot;ERROR: SECURITY CHECK FAILED!&quot;</param>
                                        </action>
                                    </actions>
                                </event-block>
                            </sub-events>
                        </event-block>
                    </sub-events>
                </event-block>
            </sub-events>
        </event-group>
        <event-block sid="499493102815705">
            <conditions>
                <condition id="-14" name="Compare variable" sid="833143531766158" type="System">
                    <param id="0" name="Variable">LogInPressed</param>
                    <param id="1" name="Comparison">0</param>
                    <param id="2" name="Value">1</param>
                </condition>
                <condition id="-4" name="Trigger once while true" sid="816728883581790" type="System" />
            </conditions>
            <actions>
                <action id="0" name="Set text" sid="973366941703527" type="LoginButtonText">
                    <param id="0" name="Text">&quot;Connecting...&quot;</param>
                </action>
            </actions>
        </event-block>
        <event-block sid="430863015902051">
            <conditions>
                <condition id="-14" name="Compare variable" sid="517489648934719" type="System">
                    <param id="0" name="Variable">LogInPressed</param>
                    <param id="1" name="Comparison">0</param>
                    <param id="2" name="Value">0</param>
                </condition>
                <condition id="-4" name="Trigger once while true" sid="675304715788130" type="System" />
            </conditions>
            <actions>
                <action id="0" name="Set text" sid="254333853701969" type="LoginButtonText">
                    <param id="0" name="Text">&quot;Login&quot;</param>
                </action>
            </actions>
        </event-block>
    </events>
</c2eventsheet>
